pypatent/__init__.py
pypatent-1.2.0.dist-info/LICENSE
pypatent-1.2.0.dist-info/METADATA
pypatent-1.2.0.dist-info/WHEEL
pypatent-1.2.0.dist-info/top_level.txt
pypatent-1.2.0.dist-info/RECORD
