Metadata-Version: 2.1
Name: pypatent
Version: 1.2.0
Summary: Search and retrieve USPTO patent data
Home-page: http://github.com/daneads/pypatent
Author: Dan Eads
Author-email: 24708079+daneads@users.noreply.github.com
License: GNU GPLv3
Keywords: patent,uspto,scrape,scraping
Platform: UNKNOWN
Classifier: Development Status :: 3 - Alpha
Classifier: Intended Audience :: Developers
Classifier: Topic :: Internet
Classifier: License :: OSI Approved :: GNU General Public License v3 or later (GPLv3+)
Classifier: Programming Language :: Python :: 3
Requires-Python: >=3
